{
  "code": 1,
  "msg": "获取成功",
  "time": "1774092391",
  "data": [
    {
      "id": 2632,
      "category_id": 219,
      "weigh": 2644,
      "model": "85009",
      "description": "3片/件 42公斤",
      "param": "",
      "image": "/uploads/20260308/微信图片_20260308154437_3145_FpILlKlrgQXUenA9i0jaWXuHS6Z8.jpg",
      "images": "/uploads/20260308/微信图片_20260308154437_3145_FpILlKlrgQXUenA9i0jaWXuHS6Z8.jpg",
      "copy": null,
      "copy2": null,
      "time": "1772956414",
      "time_text": "2026-03-08 15:53:34",
      "image_path": "https://v-erp.cdn.xingningjt.com/uploads/20260308/微信图片_20260308154437_3145_FpILlKlrgQXUenA9i0jaWXuHS6Z8.jpg?imageView2/0/w/1000",
      "images_path": [
        "https://v-erp.cdn.xingningjt.com/uploads/20260308/微信图片_20260308154437_3145_FpILlKlrgQXUenA9i0jaWXuHS6Z8.jpg?imageView2/0/w/1000"
      ]
    },
    {
      "id": 2633,
      "category_id": 219,
      "weigh": 2642,
      "model": "82186",
      "description": "3片/件 42公斤",
      "param": "",
      "image": "/uploads/20260308/微信图片_20260308154437_3147_FrHTYqMRMGpuxE5l0pyEx4-7GMx0.jpg",
      "images": "/uploads/20260308/微信图片_20260308154437_3147_FrHTYqMRMGpuxE5l0pyEx4-7GMx0.jpg",
      "copy": null,
      "copy2": null,
      "time": "1772956425",
      "time_text": "2026-03-08 15:53:45",
      "image_path": "https://v-erp.cdn.xingningjt.com/uploads/20260308/微信图片_20260308154437_3147_FrHTYqMRMGpuxE5l0pyEx4-7GMx0.jpg?imageView2/0/w/1000",
      "images_path": [
        "https://v-erp.cdn.xingningjt.com/uploads/20260308/微信图片_20260308154437_3147_FrHTYqMRMGpuxE5l0pyEx4-7GMx0.jpg?imageView2/0/w/1000"
      ]
    },
    {
      "id": 2635,
      "category_id": 219,
      "weigh": 2641,
      "model": "82187",
      "description": "3片/件 42公斤",
      "param": "",
      "image": "/uploads/20260308/微信图片_20260308154437_3149_Fi9QRWU25mtzoZ15SOjOyQYDWXkT.jpg",
      "images": "/uploads/20260308/微信图片_20260308154437_3149_Fi9QRWU25mtzoZ15SOjOyQYDWXkT.jpg",
      "copy": null,
      "copy2": null,
      "time": "1772956452",
      "time_text": "2026-03-08 15:54:12",
      "image_path": "https://v-erp.cdn.xingningjt.com/uploads/20260308/微信图片_20260308154437_3149_Fi9QRWU25mtzoZ15SOjOyQYDWXkT.jpg?imageView2/0/w/1000",
      "images_path": [
        "https://v-erp.cdn.xingningjt.com/uploads/20260308/微信图片_20260308154437_3149_Fi9QRWU25mtzoZ15SOjOyQYDWXkT.jpg?imageView2/0/w/1000"
      ]
    },
    {
      "id": 2637,
      "category_id": 219,
      "weigh": 2639,
      "model": "82188",
      "description": "3片/件 42公斤",
      "param": "",
      "image": "/uploads/20260308/微信图片_20260308154437_3151_FitcQdnTpatRw4W4jPyZJCZXXBSI.jpg",
      "images": "/uploads/20260308/微信图片_20260308154437_3151_FitcQdnTpatRw4W4jPyZJCZXXBSI.jpg",
      "copy": null,
      "copy2": null,
      "time": "1772956485",
      "time_text": "2026-03-08 15:54:45",
      "image_path": "https://v-erp.cdn.xingningjt.com/uploads/20260308/微信图片_20260308154437_3151_FitcQdnTpatRw4W4jPyZJCZXXBSI.jpg?imageView2/0/w/1000",
      "images_path": [
        "https://v-erp.cdn.xingningjt.com/uploads/20260308/微信图片_20260308154437_3151_FitcQdnTpatRw4W4jPyZJCZXXBSI.jpg?imageView2/0/w/1000"
      ]
    },
    {
      "id": 2641,
      "category_id": 219,
      "weigh": 2638,
      "model": "82232",
      "description": "3片/件 42公斤",
      "param": "",
      "image": "/uploads/20260308/微信图片_20260308154437_3157_FuyGgnDffCoLoO4Z5NCv6KTR_f1q.jpg",
      "images": "/uploads/20260308/微信图片_20260308154437_3157_FuyGgnDffCoLoO4Z5NCv6KTR_f1q.jpg",
      "copy": null,
      "copy2": null,
      "time": "1772956531",
      "time_text": "2026-03-08 15:55:31",
      "image_path": "https://v-erp.cdn.xingningjt.com/uploads/20260308/微信图片_20260308154437_3157_FuyGgnDffCoLoO4Z5NCv6KTR_f1q.jpg?imageView2/0/w/1000",
      "images_path": [
        "https://v-erp.cdn.xingningjt.com/uploads/20260308/微信图片_20260308154437_3157_FuyGgnDffCoLoO4Z5NCv6KTR_f1q.jpg?imageView2/0/w/1000"
      ]
    },
    {
      "id": 2644,
      "category_id": 219,
      "weigh": 2637,
      "model": "82535",
      "description": "3片/件 42公斤",
      "param": "",
      "image": "/uploads/20260308/微信图片_20260308154437_3161_FkIwIUUKh8r2KuQn3Vz7Uwx42Zk2.jpg",
      "images": "/uploads/20260308/微信图片_20260308154437_3161_FkIwIUUKh8r2KuQn3Vz7Uwx42Zk2.jpg",
      "copy": null,
      "copy2": null,
      "time": "1772956558",
      "time_text": "2026-03-08 15:55:58",
      "image_path": "https://v-erp.cdn.xingningjt.com/uploads/20260308/微信图片_20260308154437_3161_FkIwIUUKh8r2KuQn3Vz7Uwx42Zk2.jpg?imageView2/0/w/1000",
      "images_path": [
        "https://v-erp.cdn.xingningjt.com/uploads/20260308/微信图片_20260308154437_3161_FkIwIUUKh8r2KuQn3Vz7Uwx42Zk2.jpg?imageView2/0/w/1000"
      ]
    },
    {
      "id": 2642,
      "category_id": 219,
      "weigh": 2635,
      "model": "82533",
      "description": "3片/件 42公斤",
      "param": "",
      "image": "/uploads/20260308/微信图片_20260308154437_3159_FvO2ugHgH4gVha3VRBoC1SSY2ikN.jpg",
      "images": "/uploads/20260308/微信图片_20260308154437_3159_FvO2ugHgH4gVha3VRBoC1SSY2ikN.jpg",
      "copy": null,
      "copy2": null,
      "time": "1772956540",
      "time_text": "2026-03-08 15:55:40",
      "image_path": "https://v-erp.cdn.xingningjt.com/uploads/20260308/微信图片_20260308154437_3159_FvO2ugHgH4gVha3VRBoC1SSY2ikN.jpg?imageView2/0/w/1000",
      "images_path": [
        "https://v-erp.cdn.xingningjt.com/uploads/20260308/微信图片_20260308154437_3159_FvO2ugHgH4gVha3VRBoC1SSY2ikN.jpg?imageView2/0/w/1000"
      ]
    },
    {
      "id": 2638,
      "category_id": 219,
      "weigh": 2633,
      "model": "82238",
      "description": "3片/件 42公斤",
      "param": "",
      "image": "/uploads/20260308/微信图片_20260308154437_3153_FqmQ1OuVqbZb9pS1dMQnxDhOw6OF.jpg",
      "images": "/uploads/20260308/微信图片_20260308154437_3153_FqmQ1OuVqbZb9pS1dMQnxDhOw6OF.jpg",
      "copy": null,
      "copy2": null,
      "time": "1772956510",
      "time_text": "2026-03-08 15:55:10",
      "image_path": "https://v-erp.cdn.xingningjt.com/uploads/20260308/微信图片_20260308154437_3153_FqmQ1OuVqbZb9pS1dMQnxDhOw6OF.jpg?imageView2/0/w/1000",
      "images_path": [
        "https://v-erp.cdn.xingningjt.com/uploads/20260308/微信图片_20260308154437_3153_FqmQ1OuVqbZb9pS1dMQnxDhOw6OF.jpg?imageView2/0/w/1000"
      ]
    },
    {
      "id": 2639,
      "category_id": 219,
      "weigh": 2632,
      "model": "82181",
      "description": "3片/件 42公斤",
      "param": "",
      "image": "/uploads/20260308/微信图片_20260308154437_3155_FhkN7q7gMl6uiCHxEANj97x9vBfr.jpg",
      "images": "/uploads/20260308/微信图片_20260308154437_3155_FhkN7q7gMl6uiCHxEANj97x9vBfr.jpg",
      "copy": null,
      "copy2": null,
      "time": "1772956521",
      "time_text": "2026-03-08 15:55:21",
      "image_path": "https://v-erp.cdn.xingningjt.com/uploads/20260308/微信图片_20260308154437_3155_FhkN7q7gMl6uiCHxEANj97x9vBfr.jpg?imageView2/0/w/1000",
      "images_path": [
        "https://v-erp.cdn.xingningjt.com/uploads/20260308/微信图片_20260308154437_3155_FhkN7q7gMl6uiCHxEANj97x9vBfr.jpg?imageView2/0/w/1000"
      ]
    }
  ]
}